helloapp/__init__.py
helloapp/admin.py
helloapp/apps.py
helloapp/urls.py
helloapp/views.py
django_helloapp-0.1.0.dist-info/LICENSE
django_helloapp-0.1.0.dist-info/METADATA
django_helloapp-0.1.0.dist-info/WHEEL
django_helloapp-0.1.0.dist-info/top_level.txt
django_helloapp-0.1.0.dist-info/RECORD
